alanfe_puc_ds_csv_converter/__init__.py
alanfe_puc_ds_csv_converter/converter.py
alanfe_puc_ds_csv_converter/model/Matrix.py
alanfe_puc_ds_csv_converter/readers.py
alanfe_puc_ds_csv_converter/utils.py
alanfe_puc_ds_csv_converter/writers.py
alanfe_puc_ds_csv_converter-0.3.6.dist-info/entry_points.txt
alanfe_puc_ds_csv_converter-0.3.6.dist-info/WHEEL
alanfe_puc_ds_csv_converter-0.3.6.dist-info/METADATA
alanfe_puc_ds_csv_converter-0.3.6.dist-info/RECORD
