Metadata-Version: 2.1
Name: alanfe-puc-ds-csv-converter
Version: 0.3.6
Summary: A simple module to make easy conversions between two type of files: `csv` and `json`.
Author: Alan Federich
Author-email: alan.federich@icloud.com
Requires-Python: >=3.8,<4.0
Classifier: Programming Language :: Python :: 3
Classifier: Programming Language :: Python :: 3.10
Classifier: Programming Language :: Python :: 3.8
Classifier: Programming Language :: Python :: 3.9
Requires-Dist: click (>=8.0.3,<9.0.0)
